README.rst
setup.py
importance_sampling/__init__.py
importance_sampling/datasets.py
importance_sampling/model_wrappers.py
importance_sampling/models.py
importance_sampling/pretrained.py
importance_sampling/reweighting.py
importance_sampling/samplers.py
importance_sampling/training.py
importance_sampling/layers/__init__.py
importance_sampling/layers/metrics.py
importance_sampling/layers/normalization.py
importance_sampling/layers/scores.py
importance_sampling/utils/__init__.py
importance_sampling/utils/functional.py
importance_sampling/utils/keras_utils.py
importance_sampling/utils/tf.py
importance_sampling/utils/tf_config.py
keras_importance_sampling.egg-info/PKG-INFO
keras_importance_sampling.egg-info/SOURCES.txt
keras_importance_sampling.egg-info/dependency_links.txt
keras_importance_sampling.egg-info/requires.txt
keras_importance_sampling.egg-info/top_level.txt