Metadata-Version: 1.2
Name: keras-importance-sampling
Version: 0.9
Summary: Accelerate training of neural networks using importance sampling.
Home-page: http://www.idiap.ch/~katharas/importance-sampling/
Maintainer: Angelos Katharopoulos
Maintainer-email: angelos.katharopoulos@idiap.ch
License: MIT
Platform: UNKNOWN
Classifier: Intended Audience :: Science/Research
Classifier: Intended Audience :: Developers
Classifier: License :: OSI Approved :: MIT License
Classifier: Topic :: Scientific/Engineering
Classifier: Programming Language :: Python
Classifier: Programming Language :: Python :: 2
Classifier: Programming Language :: Python :: 2.7
Classifier: Programming Language :: Python :: 3
Classifier: Programming Language :: Python :: 3.4
Classifier: Programming Language :: Python :: 3.5
